python_release_master/__init__.py
python_release_master/__main__.py
python_release_master/cli.py
python_release_master/core/__init__.py
python_release_master/core/ai.py
python_release_master/core/ai_utils.py
python_release_master/core/changelog.py
python_release_master/core/config.py
python_release_master/core/errors.py
python_release_master/core/git.py
python_release_master/core/logger.py
python_release_master/core/release.py
python_release_master/core/templates.py
python_release_master/core/testing.py
python_release_master/core/validation.py
python_release_master/core/validation_manager.py
python_release_master/core/validators.py
python_release_master/core/verification.py
python_release_master/core/version_manager.py
python_release_master/core/validators/__init__.py
python_release_master/core/validators/base.py
python_release_master/core/validators/hatch.py
python_release_master/core/validators/project.py
python_release_master/core/validators/structure.py
python_release_master-0.5.29.dist-info/METADATA
python_release_master-0.5.29.dist-info/WHEEL
python_release_master-0.5.29.dist-info/entry_points.txt
python_release_master-0.5.29.dist-info/licenses/LICENSE
python_release_master-0.5.29.dist-info/RECORD
