Metadata-Version: 2.4
Name: python-release-master
Version: 0.5.29
Summary: An automated Python package release management tool with AI-powered changelog generation
Author-email: Kareem Elbahrawy <kareem.elbahrawy@gmail.com>
License: MIT
License-File: LICENSE
Keywords: automation,cd,changelog,ci,pypi,release
Classifier: Development Status :: 3 - Alpha
Classifier: Intended Audience :: Developers
Classifier: License :: OSI Approved :: MIT License
Classifier: Programming Language :: Python :: 3
Classifier: Programming Language :: Python :: 3.8
Classifier: Programming Language :: Python :: 3.9
Classifier: Programming Language :: Python :: 3.10
Classifier: Programming Language :: Python :: 3.11
Classifier: Programming Language :: Python :: 3.12
Requires-Python: >=3.8.1
Requires-Dist: click>=8.0.0
Requires-Dist: openai>=1.0.0
Requires-Dist: packaging>=23.0
Requires-Dist: pyyaml>=6.0.0
Requires-Dist: requests>=2.25.0
Requires-Dist: rich>=10.0.0
Requires-Dist: toml>=0.10.0
Requires-Dist: tomli-w>=1.0.0
Requires-Dist: tomli>=2.0.0
Requires-Dist: typer>=0.9.0
Provides-Extra: dev
Requires-Dist: black>=23.0.0; extra == 'dev'
Requires-Dist: flake8>=6.0.0; extra == 'dev'
Requires-Dist: isort>=5.0.0; extra == 'dev'
Requires-Dist: mypy>=1.0.0; extra == 'dev'
Requires-Dist: pytest-cov>=4.0.0; extra == 'dev'
Requires-Dist: pytest>=7.0.0; extra == 'dev'
Requires-Dist: sphinx-rtd-theme>=1.0.0; extra == 'dev'
Requires-Dist: sphinx>=6.0.0; extra == 'dev'
